{
  "generated_by": "Tools/Map Analyzer",
  "schema_version": 1,
  "map": "Mini Putt",
  "source_vmf": "Maps/Mini Putt/Mini Putt.vmf",
  "original_filename": "eft_miniputt_v1r_d.vmf",
  "generated_at": "2026-05-08T15:27:13.297951+00:00",
  "hazard_regions": [
    {
      "id": "hazard_region_1",
      "type": "hazard_region",
      "center": [
        -4635.56,
        306.94085,
        220.25815
      ],
      "bounds": {
        "min": [
          -4777.34,
          156.4117,
          56.7583
        ],
        "max": [
          -4493.780000000001,
          457.47,
          383.758
        ],
        "center": [
          -4635.56,
          306.94085,
          220.25815
        ],
        "size": [
          283.5599999999995,
          301.05830000000003,
          326.99969999999996
        ],
        "z_range": [
          56.7583,
          383.758
        ],
        "aabb_volume": 27915340.325768482,
        "source_point_count": 60,
        "warnings": []
      },
      "confidence": 0.75,
      "reasons": [
        "Hazard or forced knockdown trigger.",
        "Source entity class `trigger_hurt` id `12654`.",
        "Brush bounds extracted from VMF side plane points."
      ],
      "source_entity_ids": [
        12654
      ],
      "source_classes": [
        "trigger_hurt"
      ],
      "needs_human_review": false
    },
    {
      "id": "hazard_region_2",
      "type": "hazard_region",
      "center": [
        -5456.0,
        1792.0,
        92.1231
      ],
      "bounds": {
        "min": [
          -5576.0,
          1744.0,
          -49.3768
        ],
        "max": [
          -5336.0,
          1840.0,
          233.623
        ],
        "center": [
          -5456.0,
          1792.0,
          92.1231
        ],
        "size": [
          240.0,
          96.0,
          282.9998
        ],
        "z_range": [
          -49.3768,
          233.623
        ],
        "aabb_volume": 6520315.392,
        "source_point_count": 27,
        "warnings": []
      },
      "confidence": 0.75,
      "reasons": [
        "Hazard or forced knockdown trigger.",
        "Source entity class `trigger_hurt` id `12752`.",
        "Brush bounds extracted from VMF side plane points."
      ],
      "source_entity_ids": [
        12752
      ],
      "source_classes": [
        "trigger_hurt"
      ],
      "needs_human_review": false
    },
    {
      "id": "hazard_region_3",
      "type": "hazard_region",
      "center": [
        -3101.28,
        2364.677,
        77.04265000000001
      ],
      "bounds": {
        "min": [
          -3259.92,
          2123.014,
          -49.7677
        ],
        "max": [
          -2942.6400000000003,
          2606.34,
          203.853
        ],
        "center": [
          -3101.28,
          2364.677,
          77.04265000000001
        ],
        "size": [
          317.27999999999975,
          483.326,
          253.6207
        ],
        "z_range": [
          -49.7677,
          203.853
        ],
        "aabb_volume": 38892651.48204486,
        "source_point_count": 30,
        "warnings": []
      },
      "confidence": 0.75,
      "reasons": [
        "Hazard or forced knockdown trigger.",
        "Source entity class `trigger_hurt` id `13151`.",
        "Brush bounds extracted from VMF side plane points."
      ],
      "source_entity_ids": [
        13151
      ],
      "source_classes": [
        "trigger_hurt"
      ],
      "needs_human_review": false
    },
    {
      "id": "hazard_region_4",
      "type": "hazard_region",
      "center": [
        4699.56,
        -306.93989999999997,
        220.25815
      ],
      "bounds": {
        "min": [
          4557.780000000001,
          -457.46799999999996,
          56.7583
        ],
        "max": [
          4841.34,
          -156.4118,
          383.758
        ],
        "center": [
          4699.56,
          -306.93989999999997,
          220.25815
        ],
        "size": [
          283.5599999999995,
          301.0562,
          326.99969999999996
        ],
        "z_range": [
          56.7583,
          383.758
        ],
        "aabb_volume": 27915145.605295125,
        "source_point_count": 60,
        "warnings": []
      },
      "confidence": 0.75,
      "reasons": [
        "Hazard or forced knockdown trigger.",
        "Source entity class `trigger_hurt` id `14514`.",
        "Brush bounds extracted from VMF side plane points."
      ],
      "source_entity_ids": [
        14514
      ],
      "source_classes": [
        "trigger_hurt"
      ],
      "needs_human_review": false
    },
    {
      "id": "hazard_region_5",
      "type": "hazard_region",
      "center": [
        3165.28,
        -2364.6805,
        77.04315000000001
      ],
      "bounds": {
        "min": [
          3006.6400000000003,
          -2606.35,
          -49.7677
        ],
        "max": [
          3323.92,
          -2123.011,
          203.854
        ],
        "center": [
          3165.28,
          -2364.6805,
          77.04315000000001
        ],
        "size": [
          317.27999999999975,
          483.33899999999994,
          253.6217
        ],
        "z_range": [
          -49.7677,
          203.854
        ],
        "aabb_volume": 38893850.92992683,
        "source_point_count": 30,
        "warnings": []
      },
      "confidence": 0.75,
      "reasons": [
        "Hazard or forced knockdown trigger.",
        "Source entity class `trigger_hurt` id `14525`.",
        "Brush bounds extracted from VMF side plane points."
      ],
      "source_entity_ids": [
        14525
      ],
      "source_classes": [
        "trigger_hurt"
      ],
      "needs_human_review": false
    },
    {
      "id": "hazard_region_6",
      "type": "hazard_region",
      "center": [
        5520.0,
        -1792.0,
        92.1231
      ],
      "bounds": {
        "min": [
          5400.0,
          -1840.0,
          -49.3768
        ],
        "max": [
          5640.0,
          -1744.0,
          233.623
        ],
        "center": [
          5520.0,
          -1792.0,
          92.1231
        ],
        "size": [
          240.0,
          96.0,
          282.9998
        ],
        "z_range": [
          -49.3768,
          233.623
        ],
        "aabb_volume": 6520315.392,
        "source_point_count": 27,
        "warnings": []
      },
      "confidence": 0.75,
      "reasons": [
        "Hazard or forced knockdown trigger.",
        "Source entity class `trigger_hurt` id `14528`.",
        "Brush bounds extracted from VMF side plane points."
      ],
      "source_entity_ids": [
        14528
      ],
      "source_classes": [
        "trigger_hurt"
      ],
      "needs_human_review": false
    }
  ]
}
